uai_annotation_requests/__init__.py
uai_annotation_requests/_hooks/__init__.py
uai_annotation_requests/_hooks/sdkhooks.py
uai_annotation_requests/_hooks/types.py
uai_annotation_requests/_version.py
uai_annotation_requests/annotation_request.py
uai_annotation_requests/basesdk.py
uai_annotation_requests/clips.py
uai_annotation_requests/httpclient.py
uai_annotation_requests/models/__init__.py
uai_annotation_requests/models/annotationrequestcondenseddto.py
uai_annotation_requests/models/annotationrequestdto.py
uai_annotation_requests/models/annotationrequestexportnotreadydto.py
uai_annotation_requests/models/annotationrequestexportreferencedto.py
uai_annotation_requests/models/annotationrequestnotfounddto.py
uai_annotation_requests/models/annotationrequestphase.py
uai_annotation_requests/models/apierror.py
uai_annotation_requests/models/clipbusinessstate.py
uai_annotation_requests/models/clipdto.py
uai_annotation_requests/models/clipexporturl.py
uai_annotation_requests/models/clipreferenceidselection.py
uai_annotation_requests/models/clipslist.py
uai_annotation_requests/models/createannotationrequestdto.py
uai_annotation_requests/models/createclipdto.py
uai_annotation_requests/models/createop.py
uai_annotation_requests/models/errordetails.py
uai_annotation_requests/models/filterfield.py
uai_annotation_requests/models/getannotationsop.py
uai_annotation_requests/models/getbyannotationrequestidop.py
uai_annotation_requests/models/getclipsop.py
uai_annotation_requests/models/getexportedannotationsop.py
uai_annotation_requests/models/getfilteredop.py
uai_annotation_requests/models/getop.py
uai_annotation_requests/models/no_response_error.py
uai_annotation_requests/models/publicapidataintakestrategy.py
uai_annotation_requests/models/publicapiexportstrategy.py
uai_annotation_requests/models/responsevalidationerror.py
uai_annotation_requests/models/restartannotationrequestop.py
uai_annotation_requests/models/restartresult.py
uai_annotation_requests/models/reviewdetails.py
uai_annotation_requests-0.6.1.dist-info/LICENSE
uai_annotation_requests-0.6.1.dist-info/METADATA
uai_annotation_requests-0.6.1.dist-info/WHEEL
uai_annotation_requests-0.6.1.dist-info/RECORD
